{
  "slug": "ana-mayordomo-vs-shye-lilly-full-match-confronto-intenso-e-tecnica-feminina",
  "tags": ["superluta", "grappling feminino", "UFCBJJ", "controle de pegadas", "scramble", "análise técnica"],
  "atletas": ["Ana Mayordomo", "Shye Lilly"],
  "evento": "UFCBJJ",
  "data": "2026-03-11",
  "confianca": "baixa",
  "angulos_usados": [],
  "embedding_ref": null,
  "source_url": "https://alohabjjnews.com/ana-mayordomo-vs-shye-lilly-full-match-confronto-intenso-e-tecnica-feminina/",
  "source": "alohabjjnews-backfill"
}
